pdf_ai_extractor/__init__.py
pdf_ai_extractor/cli.py
pdf_ai_extractor/handlers/__init__.py
pdf_ai_extractor/handlers/base_handler.py
pdf_ai_extractor/handlers/huggingface_handler.py
pdf_ai_extractor/handlers/local_handler.py
pdf_ai_extractor/handlers/openai_handler.py
pdf_ai_extractor/handlers/xai_handler.py
pdf_ai_extractor-1.0.1.dist-info/licenses/LICENSE
pdf_ai_extractor-1.0.1.dist-info/METADATA
pdf_ai_extractor-1.0.1.dist-info/WHEEL
pdf_ai_extractor-1.0.1.dist-info/entry_points.txt
pdf_ai_extractor-1.0.1.dist-info/top_level.txt
pdf_ai_extractor-1.0.1.dist-info/RECORD
